{
	"folders": {},
	"connections": {
		"derby-18c027c896d-3b45f36b4585aac7": {
			"provider": "generic",
			"driver": "derby",
			"name": "database",
			"save-password": true,
			"configuration": {
				"database": "C:\\Users\\hecto\\git\\biblioteca\\database",
				"url": "jdbc:derby:C:\\Users\\hecto\\git\\biblioteca\\database",
				"configurationType": "MANUAL",
				"type": "dev",
				"auth-model": "native"
			}
		}
	},
	"connection-types": {
		"dev": {
			"name": "Development",
			"color": "255,255,255",
			"description": "Regular development database",
			"auto-commit": true,
			"confirm-execute": false,
			"confirm-data-change": false,
			"smart-commit": false,
			"smart-commit-recover": false,
			"auto-close-transactions": true,
			"close-transactions-period": 1800
		}
	}
}